threepid_checker/__init__.py
threepid_checker/py.typed
threepid_checker-1.0.1.dist-info/LICENSE
threepid_checker-1.0.1.dist-info/METADATA
threepid_checker-1.0.1.dist-info/WHEEL
threepid_checker-1.0.1.dist-info/top_level.txt
threepid_checker-1.0.1.dist-info/RECORD
