Metadata-Version: 2.1
Name: threepid-checker
Version: 1.0.1
Summary: A module that checks whether a 3PID (email address, phone number) can be allowed to register by querying a remote backend.
Classifier: License :: OSI Approved :: Apache Software License
Requires-Python: >=3.7
License-File: LICENSE
Requires-Dist: attrs
Provides-Extra: dev
Requires-Dist: matrix-synapse ; extra == 'dev'
Requires-Dist: tox ; extra == 'dev'
Requires-Dist: twisted ; extra == 'dev'
Requires-Dist: aiounittest ; extra == 'dev'
Requires-Dist: mypy (==0.910) ; extra == 'dev'
Requires-Dist: black (>=22.3.0) ; extra == 'dev'
Requires-Dist: flake8 (==4.0.1) ; extra == 'dev'
Requires-Dist: isort (==5.9.3) ; extra == 'dev'
